lap/_lapjvs_batch_wp.py
lap/_lapjv_wp.py
lap/_lapjvs.cpython-313-darwin.so
lap/__init__.py
lap/_lapjv.cpython-313-darwin.so
lap/_lapjvs_wp.py
lap/_lapmod_wp.py
lap/_lapjvx_batch_wp.py
lap/_lapjvc.cpython-313-darwin.so
lap/_lapjvx.cpython-313-darwin.so
lap/_lapjvx_wp.py
lap/_lapjvc_wp.py
lapx-0.9.4.dist-info/RECORD
lapx-0.9.4.dist-info/WHEEL
lapx-0.9.4.dist-info/top_level.txt
lapx-0.9.4.dist-info/METADATA
lapx-0.9.4.dist-info/licenses/LICENSE
lapx-0.9.4.dist-info/licenses/NOTICE
