Metadata-Version: 2.1
Name: lapx
Version: 0.9.4
Summary: Linear assignment problem solvers, including single and batch solvers.
Home-page: https://github.com/rathaROG/lapx
Author: Ratha SIV
Maintainer: rathaROG
License: MIT
Keywords: Linear Assignment Problem Solver,LAP solver,Jonker-Volgenant Algorithm,LAPJV,LAPMOD,lap,lapx,lapjvx,lapjvxa,lapjvc,lapjvs,lapjvsa,lapjvx_batch,lapjvxa_batch,lapjvs_batch,lapjvsa_batch
Classifier: Development Status :: 4 - Beta
Classifier: Environment :: Console
Classifier: Intended Audience :: Developers
Classifier: Intended Audience :: Education
Classifier: Intended Audience :: Science/Research
Classifier: Programming Language :: Python :: 3
Classifier: Programming Language :: Python :: 3.7
Classifier: Programming Language :: Python :: 3.8
Classifier: Programming Language :: Python :: 3.9
Classifier: Programming Language :: Python :: 3.10
Classifier: Programming Language :: Python :: 3.11
Classifier: Programming Language :: Python :: 3.12
Classifier: Programming Language :: Python :: 3.13
Classifier: Programming Language :: Python :: 3.14
Classifier: Topic :: Education
Classifier: Topic :: Education :: Testing
Classifier: Topic :: Scientific/Engineering
Classifier: Topic :: Scientific/Engineering :: Mathematics
Classifier: Topic :: Software Development
Classifier: Topic :: Software Development :: Libraries
Classifier: Operating System :: Microsoft :: Windows
Classifier: Operating System :: POSIX
Classifier: Operating System :: Unix
Classifier: Operating System :: MacOS
Requires-Python: >=3.7
License-File: LICENSE
License-File: NOTICE
Requires-Dist: numpy >=1.21.6
